beyond_accuracy/__init__.py
beyond_accuracy/config.py
beyond_accuracy/evaluator.py
beyond_accuracy/report.py
beyond_accuracy/metrics/__init__.py
beyond_accuracy/metrics/bias.py
beyond_accuracy/metrics/dataset.py
beyond_accuracy/metrics/explainability.py
beyond_accuracy/metrics/robustness.py
beyondaccuracy_ml-0.1.0.dist-info/METADATA
beyondaccuracy_ml-0.1.0.dist-info/WHEEL
beyondaccuracy_ml-0.1.0.dist-info/top_level.txt
beyondaccuracy_ml-0.1.0.dist-info/RECORD
