Metadata-Version: 2.4
Name: beyondaccuracy-ml
Version: 0.1.0
Summary: Beyond Accuracy test package
Requires-Python: >=3.9
